pythonvideoannotator_module_patheditor/__init__.py
pythonvideoannotator_module_patheditor/constants.py
pythonvideoannotator_module_patheditor/module.py
Python_video_annotator_module_path_editor_shaliulab-0.5.31.dist-info/METADATA
Python_video_annotator_module_path_editor_shaliulab-0.5.31.dist-info/WHEEL
Python_video_annotator_module_path_editor_shaliulab-0.5.31.dist-info/top_level.txt
Python_video_annotator_module_path_editor_shaliulab-0.5.31.dist-info/RECORD
