Metadata-Version: 2.1
Name: Python-video-annotator-module-path-editor-shaliulab
Version: 0.5.31
Home-page: https://bitbucket.org/fchampalimaud/pythonvideoannotator-module-patheditor
Author: ['Ricardo Ribeiro']
Author-email: ricardojvr@gmail.com
Requires-Dist: confapp-shaliulab (>=1.1.13)
